face_detection_sdk/__init__.py
face_detection_sdk/demo.py
face_detection_sdk/face_analyzer.py
face_detection_sdk/models.py
face_detection_sdk/utils.py
face_detection_sdk-1.0.0.dist-info/licenses/LICENSE
tests/__init__.py
tests/test_face_analyzer.py
face_detection_sdk-1.0.0.dist-info/METADATA
face_detection_sdk-1.0.0.dist-info/WHEEL
face_detection_sdk-1.0.0.dist-info/entry_points.txt
face_detection_sdk-1.0.0.dist-info/top_level.txt
face_detection_sdk-1.0.0.dist-info/RECORD
