Metadata-Version: 2.4
Name: face-detection-sdk
Version: 1.0.0
Summary: 一个基于MediaPipe和YOLO的面部检测和分析SDK
Home-page: https://github.com/yourusername/face-detection-sdk
Author: Your Name
Author-email: Your Name <your.email@example.com>
Maintainer-email: Your Name <your.email@example.com>
License: MIT
Project-URL: Homepage, https://github.com/yourusername/face-detection-sdk
Project-URL: Documentation, https://github.com/yourusername/face-detection-sdk/blob/main/README.md
Project-URL: Repository, https://github.com/yourusername/face-detection-sdk
Project-URL: Bug Tracker, https://github.com/yourusername/face-detection-sdk/issues
Keywords: face detection,computer vision,mediapipe,yolo,pose estimation
Classifier: Development Status :: 4 - Beta
Classifier: Intended Audience :: Developers
Classifier: License :: OSI Approved :: MIT License
Classifier: Operating System :: OS Independent
Classifier: Programming Language :: Python :: 3
Classifier: Programming Language :: Python :: 3.7
Classifier: Programming Language :: Python :: 3.8
Classifier: Programming Language :: Python :: 3.9
Classifier: Programming Language :: Python :: 3.10
Classifier: Programming Language :: Python :: 3.11
Classifier: Topic :: Scientific/Engineering :: Artificial Intelligence
Classifier: Topic :: Software Development :: Libraries :: Python Modules
Requires-Python: >=3.7
License-File: LICENSE
Requires-Dist: opencv-python>=4.5.0
Requires-Dist: numpy>=1.19.0
Requires-Dist: mediapipe>=0.8.0
Requires-Dist: ultralytics>=8.0.0
Requires-Dist: scipy>=1.7.0
Requires-Dist: matplotlib>=3.3.0
Provides-Extra: dev
Requires-Dist: pytest>=6.0; extra == "dev"
Requires-Dist: pytest-cov>=2.0; extra == "dev"
Requires-Dist: black>=21.0; extra == "dev"
Requires-Dist: flake8>=3.8; extra == "dev"
Requires-Dist: mypy>=0.800; extra == "dev"
Dynamic: author
Dynamic: home-page
Dynamic: license-file
Dynamic: requires-python
